jax_healpy/__init__.py
jax_healpy/_query_disc.py
jax_healpy/pixelfunc.py
jax_healpy/sphtfunc.py
jax_healpy/clustering/__init__.py
jax_healpy/clustering/_clustering.py
jax_healpy/clustering/_kmeans.py
jax_healpy-0.5.dist-info/LICENSE
jax_healpy-0.5.dist-info/METADATA
jax_healpy-0.5.dist-info/WHEEL
jax_healpy-0.5.dist-info/top_level.txt
jax_healpy-0.5.dist-info/RECORD
