Metadata-Version: 2.2
Name: jax-healpy
Version: 0.5
Summary: Healpix JAX implementation.
Author: Wassim Kabalan
Author-email: Pierre Chanial <pierre.chanial@gmail.com>, Simon Biquard <sbiquard@gmail.com>
Maintainer-email: Pierre Chanial <pierre.chanial@gmail.com>
License:                     GNU GENERAL PUBLIC LICENSE
Project-URL: homepage, https://jax-healpy.readthedocs.io
Project-URL: repository, https://github.com/CMBSciPol/jax-healpy
Keywords: scientific computing
Classifier: Programming Language :: Python
Classifier: Programming Language :: Python :: 3.9
Classifier: Programming Language :: Python :: 3.10
Classifier: Programming Language :: Python :: 3.11
Classifier: Intended Audience :: Science/Research
Classifier: Operating System :: OS Independent
Classifier: Topic :: Scientific/Engineering
Requires-Python: >=3.8
License-File: LICENSE
Requires-Dist: jax
Requires-Dist: jaxtyping
Requires-Dist: typing-extensions; python_version < "3.11"
Provides-Extra: test
Requires-Dist: healpy; extra == "test"
Requires-Dist: matplotlib; extra == "test"
Requires-Dist: pandas; extra == "test"
Requires-Dist: pytest; extra == "test"
Requires-Dist: pytest-cov; extra == "test"
Requires-Dist: pytest-mock; extra == "test"
Requires-Dist: setuptools_scm; extra == "test"
Requires-Dist: typer; extra == "test"
Requires-Dist: PyYAML; extra == "test"
Requires-Dist: chex; extra == "test"
Provides-Extra: recommended
Requires-Dist: s2fft; extra == "recommended"
